CHANGES.rst
CONTRIBUTORS.rst
MANIFEST.in
README.rst
setup.cfg
setup.py
docs/source/conf.py
docs/source/index.rst
docs/source/_static/empty
docs/source/_static/logo.png
docs/source/_templates/empty
src/ps/__init__.py
src/ps.diazo.vanilla.egg-info/PKG-INFO
src/ps.diazo.vanilla.egg-info/SOURCES.txt
src/ps.diazo.vanilla.egg-info/dependency_links.txt
src/ps.diazo.vanilla.egg-info/entry_points.txt
src/ps.diazo.vanilla.egg-info/namespace_packages.txt
src/ps.diazo.vanilla.egg-info/not-zip-safe
src/ps.diazo.vanilla.egg-info/requires.txt
src/ps.diazo.vanilla.egg-info/top_level.txt
src/ps/diazo/__init__.py
src/ps/diazo/vanilla/__init__.py
src/ps/diazo/vanilla/config.py
src/ps/diazo/vanilla/configure.zcml
src/ps/diazo/vanilla/interfaces.py
src/ps/diazo/vanilla/migration.py
src/ps/diazo/vanilla/profiles.zcml
src/ps/diazo/vanilla/setuphandlers.py
src/ps/diazo/vanilla/testing.py
src/ps/diazo/vanilla/Extensions/install.py
src/ps/diazo/vanilla/diazo_resources/favicon.ico
src/ps/diazo/vanilla/diazo_resources/index.html
src/ps/diazo/vanilla/diazo_resources/manifest.cfg
src/ps/diazo/vanilla/diazo_resources/preview.png
src/ps/diazo/vanilla/diazo_resources/rules.xml
src/ps/diazo/vanilla/diazo_resources/css/styles.css
src/ps/diazo/vanilla/diazo_resources/images/Print-icon.png
src/ps/diazo/vanilla/diazo_resources/images/arrow-bottom-black-90.png
src/ps/diazo/vanilla/diazo_resources/images/arrow-bottom-black.png
src/ps/diazo/vanilla/diazo_resources/images/arrow-bottom-black@2x.png
src/ps/diazo/vanilla/diazo_resources/images/arrow-bottom-white-90.png
src/ps/diazo/vanilla/diazo_resources/images/arrow-bottom-white.png
src/ps/diazo/vanilla/diazo_resources/images/arrow-bottom-white@2x.png
src/ps/diazo/vanilla/diazo_resources/images/arrow-left-black.png
src/ps/diazo/vanilla/diazo_resources/images/arrow-left-black@2x.png
src/ps/diazo/vanilla/diazo_resources/images/arrow-left-white.png
src/ps/diazo/vanilla/diazo_resources/images/arrow-left-white@2x.png
src/ps/diazo/vanilla/diazo_resources/images/arrow-right-black.png
src/ps/diazo/vanilla/diazo_resources/images/arrow-right-black@2x.png
src/ps/diazo/vanilla/diazo_resources/images/arrow-right-white.png
src/ps/diazo/vanilla/diazo_resources/images/arrow-right-white@2x.png
src/ps/diazo/vanilla/diazo_resources/images/bedbath.png
src/ps/diazo/vanilla/diazo_resources/images/border-gray.png
